Metadata-Version: 2.1
Name: quavasaurus
Version: 0.1
Summary: A quantum computing library for quantum circuits and algorithms.
Home-page: https://github.com/pythoncodes22/Quantum_constructor
Author: Idrees ahmad
Author-email: pythoncodes22@example.com
Classifier: Programming Language :: Python :: 3
Classifier: License :: OSI Approved :: MIT License
Classifier: Operating System :: OS Independent
Requires-Python: >=3.6
Requires-Dist: numpy
